meta_spec-0.9.5.dist-info/licenses/LICENSE
metaspec/__init__.py
metaspec/generator.py
metaspec/models.py
metaspec/registry.py
metaspec/validation.py
metaspec/cli/__init__.py
metaspec/cli/contribute.py
metaspec/cli/info.py
metaspec/cli/init.py
metaspec/cli/main.py
metaspec/cli/search.py
metaspec/cli/sync.py
metaspec/templates/README.md
metaspec/templates/base/AGENTS.md.j2
metaspec/templates/base/CHANGELOG.md.j2
metaspec/templates/base/README.md.j2
metaspec/templates/base/constitution.md.j2
metaspec/templates/base/pyproject.toml.j2
metaspec/templates/base/scripts/bash/check-prerequisites.sh.j2
metaspec/templates/base/scripts/bash/create-new-feature.sh.j2
metaspec/templates/base/scripts/bash/setup-plan.sh.j2
metaspec/templates/base/specs/README.md.j2
metaspec/templates/base/templates/README.md.j2
metaspec/templates/library/README.md
metaspec/templates/library/generic/README.md
metaspec/templates/library/generic/brownfield/commands/apply.md.j2
metaspec/templates/library/generic/brownfield/commands/archive.md.j2
metaspec/templates/library/generic/brownfield/commands/proposal.md.j2
metaspec/templates/library/generic/greenfield/commands/analyze.md.j2
metaspec/templates/library/generic/greenfield/commands/clarify.md.j2
metaspec/templates/library/generic/greenfield/commands/constitution.md.j2
metaspec/templates/library/generic/greenfield/commands/generate.md.j2
metaspec/templates/library/generic/greenfield/commands/plan.md.j2
metaspec/templates/library/generic/greenfield/commands/specify.md.j2
metaspec/templates/library/generic/greenfield/commands/tasks.md.j2
metaspec/templates/library/generic/greenfield/commands/validate.md.j2
metaspec/templates/library/generic/greenfield/templates/plan-template.md.j2
metaspec/templates/library/generic/greenfield/templates/spec-template.md.j2
metaspec/templates/library/generic/greenfield/templates/tasks-template.md.j2
metaspec/templates/library/generic/greenfield/templates/validate-template.md.j2
metaspec/templates/library/sdd/README.md
meta_spec-0.9.5.dist-info/METADATA
meta_spec-0.9.5.dist-info/WHEEL
meta_spec-0.9.5.dist-info/entry_points.txt
meta_spec-0.9.5.dist-info/top_level.txt
meta_spec-0.9.5.dist-info/RECORD
