Metadata-Version: 2.4
Name: meta-spec
Version: 0.9.5
Summary: Meta-specification framework for generating Spec-Driven X (SD-X) toolkits for AI agents
Author-email: ACNet-AI <agencollabnet@gmail.com>
License: MIT
Project-URL: Homepage, https://github.com/your-org/meta-spec
Project-URL: Repository, https://github.com/your-org/meta-spec
Project-URL: Documentation, https://meta-spec.readthedocs.io
Project-URL: Bug Tracker, https://github.com/your-org/meta-spec/issues
Keywords: meta-spec,spec-driven,code-generation,meta-programming,specification,sdd
Classifier: Development Status :: 3 - Alpha
Classifier: Intended Audience :: Developers
Classifier: License :: OSI Approved :: MIT License
Classifier: Programming Language :: Python :: 3
Classifier: Programming Language :: Python :: 3.11
Classifier: Programming Language :: Python :: 3.12
Classifier: Topic :: Software Development :: Code Generators
Classifier: Topic :: Software Development :: Libraries :: Python Modules
Requires-Python: >=3.11
License-File: LICENSE
Requires-Dist: typer>=0.9.0
Requires-Dist: jsonschema>=4.20.0
Requires-Dist: jinja2>=3.1.2
Requires-Dist: pydantic>=2.5.0
Requires-Dist: rich>=13.7.0
Requires-Dist: packaging>=23.2
Provides-Extra: dev
Requires-Dist: pytest>=7.4.3; extra == "dev"
Requires-Dist: pytest-cov>=4.1.0; extra == "dev"
Requires-Dist: pytest-asyncio>=0.21.0; extra == "dev"
Requires-Dist: black>=23.12.0; extra == "dev"
Requires-Dist: ruff>=0.1.8; extra == "dev"
Requires-Dist: mypy>=1.7.1; extra == "dev"
Requires-Dist: pre-commit>=3.6.0; extra == "dev"
Provides-Extra: docs
Requires-Dist: mkdocs>=1.5.3; extra == "docs"
Requires-Dist: mkdocs-material>=9.5.0; extra == "docs"
Requires-Dist: mkdocstrings[python]>=0.24.0; extra == "docs"
Provides-Extra: spec-kit
Provides-Extra: openspec
Provides-Extra: all
Requires-Dist: meta-spec[dev,docs]; extra == "all"
Dynamic: license-file
